extensiondp/__init__.py
extensiondp/profile.py
extensiondp/py.typed
extensiondp/schemas/__init__.py
extensiondp/schemas/table1.py
extensiondp/schemas/table2.py
extensiondp-0.1.6.dist-info/METADATA
extensiondp-0.1.6.dist-info/WHEEL
extensiondp-0.1.6.dist-info/RECORD
