Metadata-Version: 2.4
Name: extensiondp
Version: 0.1.6
Summary: Extension DP (Data Package Extension Template) is a Git repository template for rapid Data Package extension development
Project-URL: homepage, https://datisthq.github.io/extensiondp
Project-URL: repository, https://github.com/datisthq/extensiondp
Author: Evgeny Karev
License-Expression: MIT
Classifier: Programming Language :: Python :: 3
Classifier: Programming Language :: Python :: 3.12
Classifier: Topic :: Software Development :: Libraries :: Python Modules
Requires-Python: >=3.12
Requires-Dist: typing-extensions>=4.15
